README.rst
setup.py
shanhe/__init__.py
shanhe/conn/__init__.py
shanhe/conn/auth.py
shanhe/conn/connection.py
shanhe/iaas/__init__.py
shanhe/iaas/connection.py
shanhe/iaas/consolidator.py
shanhe/iaas/constants.py
shanhe/iaas/errors.py
shanhe/iaas/lb_backend.py
shanhe/iaas/lb_listener.py
shanhe/iaas/monitor.py
shanhe/iaas/router_static.py
shanhe/iaas/sg_rule.py
shanhe/iaas/actions/__init__.py
shanhe/iaas/actions/alarm_policy.py
shanhe/iaas/actions/cluster.py
shanhe/iaas/actions/eip.py
shanhe/iaas/actions/image.py
shanhe/iaas/actions/instance.py
shanhe/iaas/actions/instance_groups.py
shanhe/iaas/actions/keypair.py
shanhe/iaas/actions/loadbalancer.py
shanhe/iaas/actions/migrate.py
shanhe/iaas/actions/nic.py
shanhe/iaas/actions/router.py
shanhe/iaas/actions/s2.py
shanhe/iaas/actions/sdwan.py
shanhe/iaas/actions/security_group.py
shanhe/iaas/actions/snapshot.py
shanhe/iaas/actions/tag.py
shanhe/iaas/actions/volume.py
shanhe/iaas/actions/vpc_border.py
shanhe/iaas/actions/vxnet.py
shanhe/misc/__init__.py
shanhe/misc/json_tool.py
shanhe/misc/utils.py
shanhe/ois/__init__.py
shanhe/ois/acl.py
shanhe/ois/bucket.py
shanhe/ois/connection.py
shanhe/ois/exception.py
shanhe/ois/key.py
shanhe/ois/multipart.py
shanhe/ois/util.py
shanhe_sdk.egg-info/PKG-INFO
shanhe_sdk.egg-info/SOURCES.txt
shanhe_sdk.egg-info/dependency_links.txt
shanhe_sdk.egg-info/namespace_packages.txt
shanhe_sdk.egg-info/requires.txt
shanhe_sdk.egg-info/top_level.txt