Metadata-Version: 1.0
Name: shanhe-sdk
Version: 1.0.0
Summary: Software Development Kit for ShanHe.
Home-page: https://docsv3.shanhe.com/development_docs/sdk/
Author: ShanHe Team
Author-email: zhaoshsh@jnist.cn
License: UNKNOWN
Keywords: shanhe iaas OIS sdk
Platform: UNKNOWN
